{"cameraMode":{"drawMode":0,"name":"Shaded","section":"Shading Mode"},"sceneLighting":false,"audioPlay":false,"sceneViewState":{"showFog":true,"showMaterialUpdate":false,"showSkybox":false,"showFlares":true,"showImageEffects":true,"showParticleSystems":true},"in2DMode":false,"pivot":{"x":-12.758500099182129,"y":2.0834832191467287,"z":2.306820869445801},"rotation":{"x":0.12865398824214936,"y":-0.03461543470621109,"z":0.004536024294793606,"w":0.991081953048706},"size":16.473371505737306,"orthographic":false}